pynattas/classes/generic_lightning_module.py
pynattas/classes/generic_network.py
pynattas/classes/individual.py
pynattas/classes/particle.py
pynattas/classes/wolf.py
pynattas/functions/architecture_builder.py
pynattas/functions/fitness.py
pynattas/functions/utils.py
pynattas/modules/avgpool.py
pynattas/modules/classification_head.py
pynattas/modules/conv2d.py
pynattas/modules/dropout.py
pynattas/modules/gelu.py
pynattas/modules/maxpool.py
pynattas/modules/mbconv.py
pynattas/modules/relu.py
pynattas/optimizers/ga.py
pynattas/optimizers/gwo.py
pynattas/optimizers/pso.py
pynattas-0.0.0.dist-info/LICENSE
pynattas-0.0.0.dist-info/METADATA
pynattas-0.0.0.dist-info/WHEEL
pynattas-0.0.0.dist-info/top_level.txt
pynattas-0.0.0.dist-info/RECORD
