Metadata-Version: 2.1
Name: pynattas
Version: 0.0.0
Summary: Pynattas, a powerful open-source Python package that provides a comprehensive set of tools for model building and deployment
Home-page: https://github.com/sirbastiano/PyNA-tta-S
Author: Roberto Del Prete and Andrea Mazzeo
Author-email: robertodelprete88@gmail.com
Project-URL: Source, https://github.com/sirbastiano/PyNA-tta-S
Classifier: Development Status :: 3 - Alpha
Classifier: Intended Audience :: Developers
Classifier: Intended Audience :: Science/Research
Classifier: Topic :: Scientific/Engineering :: GIS
Classifier: License :: OSI Approved :: GNU General Public License v3 (GPLv3)
Classifier: Programming Language :: Python :: 3.8
Classifier: Environment :: GPU :: NVIDIA CUDA :: 11.0
Requires-Python: >=3.8, <4
License-File: LICENSE
Requires-Dist: numpy
Requires-Dist: opencv-python
Requires-Dist: pandas
Requires-Dist: torch
Requires-Dist: torchvision
Requires-Dist: torchmetrics
Requires-Dist: pytorch-lightning
Requires-Dist: tqdm
Requires-Dist: matplotlib
Requires-Dist: seaborn
Requires-Dist: rasterio
Requires-Dist: tifffile
